{
    "common": {
        "name": "sma-speedwire",
        "version": "0.9.0",
      "news": {
        "0.9.0": {
          "en": "support more then one device"
        },
        "0.8.0": {
          "en": "make ist ready for latest ioBroker version",
          "de": "make ist bereit für die neueste ioBroker-Version",
          "ru": "подготовьтесь к последней версии ioBroker",
          "pt": "prepare-se para a versão mais recente do ioBroker",
          "nl": "maak het klaar voor de nieuwste ioBroker-versie",
          "fr": "préparer est prêt pour la dernière version d'ioBroker",
          "it": "rendilo pronto per l'ultima versione di ioBroker",
          "es": "prepárelo para la última versión de ioBroker",
          "pl": "przygotuj go na najnowszą wersję ioBroker",
          "uk": "підготуйте його до останньої версії ioBroker",
          "zh-cn": "为最新的 ioBroker 版本做好准备"
        },
        "0.7.0": {
          "en": "Rework in a lot of areas, added role and unit settings for the values",
          "de": "Überarbeitung in vielen Bereichen, bei den Werten werden nun auch die Werte für die Rolle und Unit gesetzt ",
          "ru": "Переработано множество областей, добавлены настройки ролей и единиц измерения для значений.",
          "pt": "Retrabalho em muitas áreas, adição de funções e configurações de unidade para os valores",
          "nl": "Op veel gebieden herwerkt, rol- en eenheidsinstellingen voor de waarden toegevoegd",
          "fr": "Retravail dans de nombreux domaines, ajout de paramètres de rôle et d'unité pour les valeurs",
          "it": "Rielaborazione in molte aree, aggiunta di impostazioni di ruoli e unità per i valori",
          "es": "Retrabajo en muchas áreas, configuración agregada de roles y unidades para los valores.",
          "pl": "Przerobiono wiele obszarów, dodano ustawienia ról i jednostek dla wartości",
          "uk": "Перероблено багато областей, додано налаштування ролей і підрозділів для значень",
          "zh-cn": "在很多领域进行了返工，添加了角色和单位的值设置"
        },
        "0.0.1": {
          "en": "initial adapter",
          "de": "Initiale Version",
          "ru": "первоначальный адаптер",
          "pt": "adaptador inicial",
          "nl": "initiële adapter",
          "fr": "adaptateur initial",
          "it": "adattatore iniziale",
          "es": "adaptador inicial",
          "pl": "adapter początkowy",
          "uk": "початковий адаптер",
          "zh-cn": "初始适配器"
        }
      },
        "titleLang": {
            "en": "sma-speedwire",
            "de": "sma-speedwire",
            "ru": "sma-speedwire",
            "pt": "sma-speedwire",
            "nl": "sma-speedwire",
            "fr": "sma-speedwire",
            "it": "sma-speedwire",
            "es": "sma-speedwire",
            "pl": "sma-speedwire",
            "uk": "sma-speedwire",
            "zh-cn": "SMA-高速线"
        },
        "desc": {
            "en": "Adapter to query values from sma devices",
            "de": "Adapter zum Abfragen von Werten von SMA-Invertern",
            "ru": "Адаптер для запроса значений из sma-устройств",
            "pt": "Adaptador para consultar valores de dispositivos sma",
            "nl": "Adapter om waarden op te vragen van sma-apparaten",
            "fr": "Adaptateur pour interroger les valeurs des périphériques sma",
            "it": "Adattatore per interrogare i valori dai dispositivi sma",
            "es": "Adaptador para consultar valores de dispositivos sma",
            "pl": "Adapter do wyszukiwania wartości z urządzeń sma",
            "uk": "Адаптер для запиту значень із пристроїв sma",
            "zh-cn": "用于从 sma 设备查询值的适配器"
        },
        "authors": [
            "my Name <thomasAthepper.eu>"
        ],
        "platform": "Javascript/Node.js",
        "mode": "daemon",
        "type": "energy",
        "compact": true,
        "connectionType": "local",
        "dataSource": "push",
        "icon": "sma.png",
        "materialize": true,
        "enabled": true,
        "extIcon": "https://raw.githubusercontent.com/AttackStrawbery/ioBroker.sma-speedwire/master/admin/sma.png",
        "keywords": [
            "sma-speedwire"
        ],
        "license": "MIT",
        "readme": "https://github.com/AttackStrawbery/ioBroker.sma-speedwire/blob/master/README.md",
        "loglevel": "info"
    },
    "native": {
        "ip": "0.0.0.0",
        "port": 9522,
        "user": "Benutzer",
        "password": "0000"
    }
}
